{
  "2025-2-22": [
    [
      "2025-02-22 09:55PM",
      "Penn to reduce graduate admissions, rescind acceptances amid federal research funding cuts"
    ],
    [
      "2025-02-22 10:13PM",
      ""
    ],
    [
      "2025-02-22 10:23PM",
      "Mia Vesely | Black Penn is not a monolith"
    ]
  ],
  "2025-2-24": [
    [
      "2025-02-24 12:18AM",
      "Mia Vesely | Black Penn is not a monolith"
    ],
    [
      "2025-02-24 08:16AM",
      "Mritika Senthil | NIH funding cuts aren\u2019t the crisis Penn claims"
    ]
  ],
  "2025-2-25": [
    [
      "2025-02-25 08:14AM",
      "David Tran | 34th Street takes a walk"
    ],
    [
      "2025-02-25 09:56PM",
      "Elo Esalomi | The illusion of DEI"
    ]
  ],
  "2025-2-26": [
    [
      "2025-02-26 08:14AM",
      "Eden Liu | When experience meets the exit door"
    ]
  ],
  "2025-2-27": [
    [
      "2025-02-27 08:15AM",
      "Eric Najera | Everyone should take advantage of Wharton"
    ]
  ]
}